README.txt
setup.py
docs/HISTORY.txt
docs/INSTALL.txt
docs/LICENSE.GPL
docs/LICENSE.txt
xm/__init__.py
xm.globalissues.egg-info/PKG-INFO
xm.globalissues.egg-info/SOURCES.txt
xm.globalissues.egg-info/dependency_links.txt
xm.globalissues.egg-info/entry_points.txt
xm.globalissues.egg-info/namespace_packages.txt
xm.globalissues.egg-info/not-zip-safe
xm.globalissues.egg-info/paster_plugins.txt
xm.globalissues.egg-info/requires.txt
xm.globalissues.egg-info/top_level.txt
xm/globalissues/CHANGELOG
xm/globalissues/README.txt
xm/globalissues/__init__.py
xm/globalissues/adapters.py
xm/globalissues/configure.zcml
xm/globalissues/overrides.zcml
xm/globalissues/tests.py