Metadata-Version: 1.0
Name: xm.globalissues
Version: 1.0
Summary: Find Poi issues globally in the site when adding issue tracker tasks
Home-page: http://svn.plone.org/svn/collective/xm.globalissues
Author: Hans-Peter Locher
Author-email: hans-peter.locher@inquant.de
License: GPL
Keywords: Plone
Platform: UNKNOWN
Classifier: Framework :: Plone
Classifier: Programming Language :: Python
Classifier: Topic :: Software Development :: Libraries :: Python Modules
